{
  "players": {
    "contentsGfx": [
      "gfx/charactermenu.anm2",
      "gfx/charactermenu.png",
      "gfx/characterportraits.anm2",
      "gfx/death portraits.png",
      "gfx/death screen.anm2"
    ],
    "requires": [
      "players.xml",
      "costumes2.xml"
    ],
    "resourceFolders": [
      "gfx/characters/costumes",
      "sfx/player"
    ]
  },

  "items": {
    "requires": [
      "itempools.xml",
      "items.xml",
      "costumes2.xml"
    ],
    "resourceFolders": [
      "gfx/collectibles",
      "gfx/characters/costumes"
    ]
  },

  "challenges": {
    "requires": [
      "challenges.xml"
    ]
  },

  "entities": {
    "requires": [
      "entities2.xml"
    ],
    "resourceFolders": [
      "gfx/monsters"
    ]
  },

  "pillcards": {
    "contentsGfx": [
      "gfx/ui_cardfronts.anm2",
      "gfx/ui_cardfronts.png"
    ],
    "requires": [
      "pocketitems.xml"
    ]
  },

  "curses": {
    "requires": [
      "curses.xml"
    ]
  }
}
